lms_ubitraq/__init__.py
lms_ubitraq/admin.py
lms_ubitraq/apps.py
lms_ubitraq/models.py
lms_ubitraq/serializers.py
lms_ubitraq/services.py
lms_ubitraq/tests.py
lms_ubitraq/urls.py
lms_ubitraq/utils.py
lms_ubitraq/views.py
lms_ubitraq/migrations/__init__.py
lms_ubitraq/static/lms_ubitraq/css/lib/element-plus.css
lms_ubitraq/static/lms_ubitraq/js/lib/element/dayjs.min.js
lms_ubitraq/static/lms_ubitraq/js/lib/element/element-plus.min.js
lms_ubitraq/static/lms_ubitraq/js/lib/element/zh-cn.js
lms_ubitraq/static/lms_ubitraq/js/lib/vue/vue.global.prod.js
lms_ubitraq/templates/common.html
lms_ubitraq/templates/lms_ubitraq/console.html
lms_ubitraq-0.3.0.dist-info/licenses/LICENSE
lms_ubitraq-0.3.0.dist-info/METADATA
lms_ubitraq-0.3.0.dist-info/WHEEL
lms_ubitraq-0.3.0.dist-info/top_level.txt
lms_ubitraq-0.3.0.dist-info/RECORD
